{
  "author": "chris_93606",
  "profit_percentage": "2.35",
  "symbol": "BTCUSDT ",
  "position_type": "LONG ",
  "leverage": "5x ",
  "image_url": " https://cdn.discordapp.com/attachments/1164102219998695445/1520611309086052552/BTC_Sun2.png?ex=6a41d323&is=6a4081a3&hm=285a298c5b7cf399f7d3696ed5a3576aea980b85bfa2fbd604bc31f5d663a31d&",
  "summary": "A trade on BTCUSDT showing a profit of 2.35% with a last price of 60247.7 and an average price of 59965.4. ",
  "updated_at": " 2026-06-28T06:00:52.578Z"
}